LICENSE
README.md
pyproject.toml
src/test.py
src/midas/__init__.py
src/midas/data_encoder.py
src/midas/event.py
src/midas/playfab.py
src/midas/session.py
src/midas/user.py
src/midas_data_util.egg-info/PKG-INFO
src/midas_data_util.egg-info/SOURCES.txt
src/midas_data_util.egg-info/dependency_links.txt
src/midas_data_util.egg-info/requires.txt
src/midas_data_util.egg-info/top_level.txt